restlog/__init__.py
restlog/__main__.py
restlog/backend.py
restlog/common.py
restlog/json_schema_repo.json
restlog/main.py
restlog/server.py
restlog/clients/__init__.py
restlog/clients/status/__init__.py
restlog/clients/status/linux.py
restlog/ui/index.html
restlog/ui/index.js
restlog/ui/index.js.map
restlog/ui/openapi.yaml
restlog-0.0.2.dist-info/METADATA
restlog-0.0.2.dist-info/WHEEL
restlog-0.0.2.dist-info/entry_points.txt
restlog-0.0.2.dist-info/top_level.txt
restlog-0.0.2.dist-info/RECORD
