Metadata-Version: 2.1
Name: restlog
Version: 0.0.2
Summary: JSON log-structured data storage with REST API
Home-page: https://github.com/bozokopic/restlog
License: GPLv3
Platform: UNKNOWN
Classifier: Programming Language :: Python :: 3
Classifier: License :: OSI Approved :: GNU General Public License v3 (GPLv3)
Requires-Python: >=3.8
Requires-Dist: aiohttp
Requires-Dist: aiohttp-remotes
Requires-Dist: appdirs
Requires-Dist: click
Requires-Dist: doit
Requires-Dist: hat-aio
Requires-Dist: hat-json
